kirje/__init__.py
kirje/kirje.py
kirje-0.2.0.dist-info/METADATA
kirje-0.2.0.dist-info/WHEEL
kirje-0.2.0.dist-info/licenses/LICENSE
kirje-0.2.0.dist-info/RECORD
