Metadata-Version: 2.1
Name: kirje
Version: 0.2.0
Summary: A framing library for content with headers and body.
Project-URL: Homepage, https://github.com/karrimiettinen/kirje
Project-URL: Bug Tracker, https://github.com/karrimiettinen/kirje/issues
Author-email: Karri Miettinen <karri.miettinen@lab.fi>
License-File: LICENSE
Classifier: License :: OSI Approved :: MIT License
Classifier: Operating System :: OS Independent
Classifier: Programming Language :: Python :: 3
Requires-Python: >=3.11
